LICENSE
README.md
pyproject.toml
setup.py
src/spacemodel/__init__.py
src/spacemodel/base.py
src/spacemodel/fields.py
src/spacemodel/meta.py
src/spacemodel.egg-info/PKG-INFO
src/spacemodel.egg-info/SOURCES.txt
src/spacemodel.egg-info/dependency_links.txt
src/spacemodel.egg-info/requires.txt
src/spacemodel.egg-info/top_level.txt